neo4j_graphql_py/__init__.py
neo4j_graphql_py/augment_schema.py
neo4j_graphql_py/main.py
neo4j_graphql_py/selections.py
neo4j_graphql_py/utils.py
neo4j_graphql_py-0.1.4.dist-info/LICENSE
neo4j_graphql_py-0.1.4.dist-info/METADATA
neo4j_graphql_py-0.1.4.dist-info/WHEEL
neo4j_graphql_py-0.1.4.dist-info/top_level.txt
neo4j_graphql_py-0.1.4.dist-info/RECORD
