Metadata-Version: 2.1
Name: neo4j-graphql-py
Version: 0.1.4
Summary: A GraphQL to Cypher query execution layer for Neo4j and Python GraphQL implementations.
Home-page: https://github.com/Usama0121/neo4j-graphql-py
Author: Muhammad Usama
Author-email: aslam0121@gmail.com
License: Apache 2.0
Platform: UNKNOWN
Classifier: License :: OSI Approved :: Apache Software License
Classifier: Programming Language :: Python
Classifier: Programming Language :: Python :: 3
Classifier: Programming Language :: Python :: 3.6
Classifier: Programming Language :: Python :: Implementation :: CPython
Classifier: Programming Language :: Python :: Implementation :: PyPy
Requires-Python: >=3.6.0
Requires-Dist: neo4j (==4.1.0)
Requires-Dist: graphql-core (==3.0.5)
Requires-Dist: pydash (==4.8.0)
